[
    {
        "key": "dbln",
        "value": "%7B%2261566386494006%22%3A%225wH3QqHU%22%2C%2261568232800651%22%3A%224VDrbzkx%22%7D",
        "domain": "facebook.com",
        "path": "/login/device-based/",
        "hostOnly": false,
        "creation": "2024-12-19T08:10:59.559Z",
        "lastAccessed": "2024-12-19T08:10:59.561Z"
    },
    {
        "key": "datr",
        "value": "GgkZZ-Ke1GwtUDUr_6agjva_",
        "domain": "facebook.com",
        "path": "/",
        "hostOnly": false,
        "creation": "2024-12-19T08:10:59.561Z",
        "lastAccessed": "2024-12-19T08:10:59.561Z"
    },
    {
        "key": "sb",
        "value": "GgkZZ7dE_PCfqGdBnlddx1ND",
        "domain": "facebook.com",
        "path": "/",
        "hostOnly": false,
        "creation": "2024-12-19T08:10:59.561Z",
        "lastAccessed": "2024-12-19T08:10:59.561Z"
    },
    {
        "key": "ps_l",
        "value": "1",
        "domain": "facebook.com",
        "path": "/",
        "hostOnly": false,
        "creation": "2024-12-19T08:10:59.561Z",
        "lastAccessed": "2024-12-19T08:10:59.561Z"
    },
    {
        "key": "ps_n",
        "value": "1",
        "domain": "facebook.com",
        "path": "/",
        "hostOnly": false,
        "creation": "2024-12-19T08:10:59.561Z",
        "lastAccessed": "2024-12-19T08:10:59.561Z"
    },
    {
        "key": "locale",
        "value": "en_GB",
        "domain": "facebook.com",
        "path": "/",
        "hostOnly": false,
        "creation": "2024-12-19T08:10:59.561Z",
        "lastAccessed": "2024-12-19T08:10:59.561Z"
    },
    {
        "key": "wd",
        "value": "393x785",
        "domain": "facebook.com",
        "path": "/",
        "hostOnly": false,
        "creation": "2024-12-19T08:10:59.561Z",
        "lastAccessed": "2024-12-19T08:10:59.561Z"
    },
    {
        "key": "c_user",
        "value": "100071677211067",
        "domain": "facebook.com",
        "path": "/",
        "hostOnly": false,
        "creation": "2024-12-19T08:10:59.561Z",
        "lastAccessed": "2024-12-19T08:10:59.561Z"
    },
    {
        "key": "fr",
        "value": "0YmAVeVQPIfol4HVp.AWUf24TjJf_5M1IHxKurMNgozHI.BnMx2u..AAA.0.0.BnY1qc.AWXzMHzi_9w",
        "domain": "facebook.com",
        "path": "/",
        "hostOnly": false,
        "creation": "2024-12-19T08:10:59.561Z",
        "lastAccessed": "2024-12-19T08:10:59.561Z"
    },
    {
        "key": "xs",
        "value": "5%3Amx3dOQgbz2l3Bg%3A2%3A1734564508%3A-1%3A5181",
        "domain": "facebook.com",
        "path": "/",
        "hostOnly": false,
        "creation": "2024-12-19T08:10:59.561Z",
        "lastAccessed": "2024-12-19T08:10:59.561Z"
    },
    {
        "key": "vpd",
        "value": "v1%3B785x393x2.75",
        "domain": "facebook.com",
        "path": "/",
        "hostOnly": false,
        "creation": "2024-12-19T08:10:59.561Z",
        "lastAccessed": "2024-12-19T08:10:59.561Z"
    },
    {
        "key": "fbl_st",
        "value": "100630993%3BT%3A28909930",
        "domain": "facebook.com",
        "path": "/",
        "hostOnly": false,
        "creation": "2024-12-19T08:10:59.561Z",
        "lastAccessed": "2024-12-19T08:10:59.561Z"
    },
    {
        "key": "wl_cbv",
        "value": "v2%3Bclient_version%3A2699%3Btimestamp%3A1734595854",
        "domain": "facebook.com",
        "path": "/",
        "hostOnly": false,
        "creation": "2024-12-19T08:10:59.561Z",
        "lastAccessed": "2024-12-19T08:10:59.561Z"
    }
]
